obiba_mica/__init__.py
obiba_mica/access.py
obiba_mica/annotation.py
obiba_mica/console.py
obiba_mica/core.py
obiba_mica/file.py
obiba_mica/import_zip.py
obiba_mica/perm.py
obiba_mica/plugin.py
obiba_mica/rest.py
obiba_mica/search.py
obiba_mica/update_collected_dataset.py
obiba_mica/update_collected_datasets.py
obiba_mica-5.1.0.dist-info/LICENSE.txt
obiba_mica-5.1.0.dist-info/METADATA
obiba_mica-5.1.0.dist-info/WHEEL
obiba_mica-5.1.0.dist-info/entry_points.txt
obiba_mica-5.1.0.dist-info/RECORD
