Metadata-Version: 2.1
Name: obiba-mica
Version: 5.1.0
Summary: OBiBa/Mica python client.
Home-page: https://www.obiba.org
License: GPL-v3
Author: Yannick Marcon
Author-email: yannick.marcon@obiba.org
Requires-Python: >=3.7,<4.0
Classifier: License :: Other/Proprietary License
Classifier: Programming Language :: Python :: 3
Classifier: Programming Language :: Python :: 3.7
Classifier: Programming Language :: Python :: 3.8
Classifier: Programming Language :: Python :: 3.9
Classifier: Programming Language :: Python :: 3.10
Classifier: Programming Language :: Python :: 3.11
Requires-Dist: requests (>=2.31.0,<3.0.0)
Requires-Dist: urllib3 (==1.26.15)
Project-URL: Bug Tracker, https://github.com/obiba/mica-python-client/issues
Project-URL: Documentation, https://micadoc.obiba.org/en/latest/python-user-guide/
Project-URL: Repository, https://github.com/obiba/mica-python-client
